sbol/CRISPR_example.py
sbol/sbol.py
sbol/_libsbol.so
sbol/crispr_example.xml
sbol/unit_tests.py
sbol/__init__.py
sbol/libsbol.py
sbol/.libs/libxslt-6cbe83bf.so.1.1.17
sbol/.libs/libz-a147dcb0.so.1.2.3
sbol/.libs/libxml2-8ed442f7.so.2.6.26
sbol/test/design-build-test-learn2.xml
sbol/test/pom.xml
sbol/test/README.md
sbol/test/manifest.sh
sbol/test/SBOL2_nc/SBOL1and2Test.xml
sbol/test/SBOL2_nc/pIKE_pTAK_left_right_cassettes_orig.xml
sbol/test/SBOL2_nc/igem2.xml
sbol/test/SBOL2_nc/pIKE_pTAK_toggle_switches_orig.xml
sbol/test/SBOL2_nc/partial_pTAK_right_cassette_orig.xml
sbol/test/SBOL2_nc/pIKE_pTAK_cassettes_2_orig.xml
sbol/test/SBOL2_nc/labhost_All_orig.xml
sbol/test/SBOL2_nc/labhost_Insect_Cells_orig.xml
sbol/test/SBOL2_nc/BBa_T9002_orig.xml
sbol/test/SBOL2_nc/partial_pIKE_left_cassette_orig.xml
sbol/test/SBOL2_nc/labhost_Bacillus_subtilis_orig.xml
sbol/test/SBOL2_nc/igem1.xml
sbol/test/SBOL2_nc/BBa_I0462_orig.xml
sbol/test/SBOL2_nc/labhost_Drosophila_melanogaster_orig.xml
sbol/test/SBOL2_nc/partial_pIKE_right_cassette_orig.xml
sbol/test/SBOL2_nc/partial_pTAK_left_cassette_orig.xml
sbol/test/SBOL2_nc/pIKE_pTAK_cassettes_orig.xml
sbol/test/SBOL2_nc/labhost_Mammalian_Cells_orig.xml
sbol/test/SBOL2_nc/labhost_Schizosaccharomyces_pombe_orig.xml
sbol/test/SBOL2_nc/labhost_Plant_Cells_orig.xml
sbol/test/SBOL2_nc/labhost_Kluyveromyces_lactis_orig.xml
sbol/test/SBOL2_nc/igem3.xml
sbol/test/SBOL2_nc/labhost_Saccharomyces_cerevisiae_orig.xml
sbol/test/SBOL2_nc/labhost_Gram-negative_bacteria_orig.xml
sbol/test/SBOL2_nc/labhost_Unspecified_orig.xml
sbol/test/SBOL2_nc/labhost_Aspergillus_nidulans_orig.xml
sbol/test/SBOL2_nc/partial_pIKE_right_casette_orig.xml
sbol/test/SBOL2_nc/was-generated-bys-derived-froms.xml
sbol/test/SBOL2_nc/labhost_Pichia_pastoris_orig.xml
sbol/test/SBOL2_nc/labhost_Escherichia_Coli_orig.xml
sbol/test/SBOL2/SBOL1and2Test.xml
sbol/test/SBOL2/pIKE_pTAK_left_right_cassettes_orig.xml
sbol/test/SBOL2/pICH45173.xml
pySBOL-2.3.3.post9.dist-info/RECORD
pySBOL-2.3.3.post9.dist-info/METADATA
pySBOL-2.3.3.post9.dist-info/top_level.txt
pySBOL-2.3.3.post9.dist-info/WHEEL
