Metadata-Version: 2.1
Name: pySBOL
Version: 2.3.3.post9
Summary: A module for reading, writing, and constructing genetic designs according to the standardized specifications of the Synthetic Biology Open Language (SBOL).
Home-page: https://github.com/SynBioDex/pySBOL
Author: Bryan Bartley
Author-email: editors@sbolstandard.org
License: Apache-2
Keywords: synthetic biology
Platform: UNKNOWN
Classifier: Development Status :: 5 - Production/Stable
Classifier: Intended Audience :: Developers
Classifier: License :: OSI Approved :: Apache Software License
Classifier: Programming Language :: Python :: 2
Classifier: Programming Language :: Python :: 2.7
Classifier: Programming Language :: Python :: 3
Classifier: Programming Language :: Python :: 3.6
Requires-Dist: requests
Requires-Dist: distro
